shantenx-0.1.12.dist-info/METADATA
shantenx-0.1.12.dist-info/WHEEL
shantenx/__init__.py
shantenx/shantenx.cpython-311-x86_64-linux-gnu.so
shantenx-0.1.12.dist-info/RECORD
