Metadata-Version: 2.1
Name: shantenx
Version: 0.1.12
